image_intensities
sources
