Metadata-Version: 2.1
Name: image-intensities
Version: 0.1.0
Summary: Calculate image intensities, a database friendly alternative to image hashing..
Home-page: https://github.com/luckydonald/image_intensities
Author: luckydonald
Author-email: image_intensities+code@luckydonald.de
License: GPLv3+
Project-URL: Code, https://github.com/luckydonald/image_intensities
Project-URL: Issue tracker, https://github.com/luckydonald/image_intensities/issues
Keywords: image hash image hashing image intensities nw sw se ne derpibooru
Platform: UNKNOWN
Classifier: Development Status :: 4 - Beta
Classifier: Intended Audience :: Developers
Classifier: Intended Audience :: Science/Research
Classifier: Intended Audience :: System Administrators
Classifier: Intended Audience :: Telecommunications Industry
Classifier: Topic :: Utilities
Classifier: Topic :: Software Development :: Libraries
Classifier: Topic :: Software Development :: Libraries :: Python Modules
Classifier: Environment :: Plugins
Classifier: License :: OSI Approved :: GNU General Public License v3 or later (GPLv3+)
Classifier: Programming Language :: Python :: 3
Classifier: Programming Language :: Python :: 3 :: Only
Classifier: Operating System :: MacOS :: MacOS X
Classifier: Operating System :: Unix
